sqlalembic/__init__.py
sqlalembic/main.py
sqlalembic/conf/alembic_template/README.md.template
sqlalembic/conf/alembic_template/alembic.ini.template
sqlalembic/conf/alembic_template/env.py.template
sqlalembic/conf/alembic_template/script.py.mako.template
sqlalembic/conf/project_templates/env.template
sqlalembic/conf/project_templates/manage.py.template
sqlalembic/core/__init__.py
sqlalembic/core/config.py
sqlalembic/core/error_handler.py
sqlalembic/core/initialize_core.py
sqlalembic/core/logging_setup.py
sqlalembic/core/migration.py
sqlalembic/core/project_structure.py
sqlalembic/core/signals.py
sqlalembic/integrations/__init__.py
sqlalembic/integrations/alembic_setup.py
sqlalembic-1.0.0.dist-info/licenses/LICENSE
tests/__init__.py
tests/test_Integration.py
tests/test_config.py
tests/test_model_discoverer.py
tests/test_project_structure.py
tests/test_signals.py
sqlalembic-1.0.0.dist-info/METADATA
sqlalembic-1.0.0.dist-info/WHEEL
sqlalembic-1.0.0.dist-info/entry_points.txt
sqlalembic-1.0.0.dist-info/top_level.txt
sqlalembic-1.0.0.dist-info/RECORD
