Metadata-Version: 2.4
Name: sqlalembic
Version: 1.0.0
Summary: A comprehensive Python framework for SQLAlchemy model discovery, configuration management, and database migrations with Alembic integration
Home-page: https://github.com/hemaabokila/sqlalembic_framework
Author: Ibrahem Abokila
Author-email: ibrahemabokila@gmail.com
License: MIT
Classifier: Development Status :: 3 - Alpha
Classifier: Intended Audience :: Developers
Classifier: License :: OSI Approved :: MIT License
Classifier: Programming Language :: Python :: 3
Classifier: Programming Language :: Python :: 3.8
Classifier: Programming Language :: Python :: 3.9
Classifier: Programming Language :: Python :: 3.10
Classifier: Programming Language :: Python :: 3.11
Classifier: Programming Language :: Python :: 3.12
Classifier: Operating System :: OS Independent
Classifier: Topic :: Database
Classifier: Topic :: Software Development :: Libraries :: Application Frameworks
Requires-Python: >=3.8
License-File: LICENSE
Requires-Dist: alembic~=1.16.4
Requires-Dist: PyMySQL~=1.1.1
Requires-Dist: python-dotenv~=1.1.1
Requires-Dist: PyYAML~=6.0.2
Requires-Dist: SQLAlchemy~=2.0.42
Requires-Dist: toml~=0.10.2
Requires-Dist: psycopg2-binary~=2.9.10
Provides-Extra: testing
Requires-Dist: pytest~=8.3.5; extra == "testing"
Dynamic: author
Dynamic: author-email
Dynamic: classifier
Dynamic: description
Dynamic: description-content-type
Dynamic: home-page
Dynamic: license
Dynamic: license-file
Dynamic: provides-extra
Dynamic: requires-dist
Dynamic: requires-python
Dynamic: summary
